devbricksxai/__init__.py
devbricksxai/generativeai/__init__.py
devbricksxai/generativeai/genai.py
devbricksxai/generativeai/taskforce.py
devbricksxai/generativeai/roles/__init__.py
devbricksxai/generativeai/roles/advisor.py
devbricksxai/generativeai/roles/artisan.py
devbricksxai/generativeai/roles/character.py
devbricksxai/generativeai/roles/advisors/__init__.py
devbricksxai/generativeai/roles/advisors/chatgpt.py
devbricksxai/generativeai/roles/advisors/gemini.py
devbricksxai/generativeai/roles/artisans/__init__.py
devbricksxai/generativeai/roles/artisans/analyst.py
devbricksxai/generativeai/roles/artisans/escort.py
devbricksxai/generativeai/roles/artisans/historian.py
devbricksxai/generativeai/roles/artisans/musician.py
devbricksxai/generativeai/roles/artisans/painter.py
devbricksxai/generativeai/roles/artisans/analysts/__init__.py
devbricksxai/generativeai/roles/artisans/analysts/news/__init__.py
devbricksxai/generativeai/roles/artisans/analysts/news/news_ai_analyst.py
devbricksxai/generativeai/roles/artisans/analysts/news/news_analyst.py
devbricksxai/generativeai/roles/artisans/analysts/news/newssite/__init__.py
devbricksxai/generativeai/roles/artisans/analysts/news/newssite/bbc.py
devbricksxai/generativeai/roles/artisans/analysts/news/newssite/ccn.py
devbricksxai/generativeai/roles/artisans/analysts/news/newssite/chinanews.py
devbricksxai/generativeai/roles/artisans/analysts/news/newssite/googleplay.py
devbricksxai/generativeai/roles/artisans/analysts/news/newssite/thepaper.py
devbricksxai/generativeai/roles/artisans/analysts/news/newssite/toutiao.py
devbricksxai/generativeai/roles/artisans/analysts/news/newssite/universal.py
devbricksxai/generativeai/roles/artisans/analysts/news/newssite/website_analyst.py
devbricksxai/generativeai/roles/artisans/analysts/news/rss/__init__.py
devbricksxai/generativeai/roles/artisans/analysts/news/rss/reddit.py
devbricksxai/generativeai/roles/artisans/analysts/news/rss/rss_analyst.py
devbricksxai-0.1.7.dist-info/licenses/LICENSE
devbricksxai-0.1.7.dist-info/METADATA
devbricksxai-0.1.7.dist-info/WHEEL
devbricksxai-0.1.7.dist-info/top_level.txt
devbricksxai-0.1.7.dist-info/RECORD
